astropixie/__init__.py
astropixie/catalog_service.py
astropixie/data.py
astropixie/sample_catalog_provider.py
astropixie/types.py
astropixie/sample_data/berkeley20-durgapal.dat
astropixie/sample_data/berkeley20.png
astropixie/sample_data/berkeley20.tsv
astropixie/sample_data/ngc2849-kyeong.dat
astropixie/sample_data/ngc7790-gupta.dat
astropixie/sample_data/ngc7790-gupta.readme.txt
astropixie/sample_data/ngc7790-petrov.dat
astropixie/sample_data/ngc7790-petrov.readme.txt
astropixie/sample_data/ngc7790-phelps.dat
astropixie-0.1.8.dist-info/METADATA
astropixie-0.1.8.dist-info/RECORD
astropixie-0.1.8.dist-info/WHEEL
astropixie-0.1.8.dist-info/top_level.txt
