Metadata-Version: 2.1
Name: astropixie
Version: 0.1.8
Summary: LSST EPO python library.
Home-page: https://github.com/lsst-epo/vela/astropixie
Author: LSST EPO Team
Author-email: epo-team@lists.lsst.org
License: MIT
Platform: UNKNOWN
Requires-Dist: astropy (<3.1,>=3.0.1)
Requires-Dist: astroquery (>=0.3.8)
Requires-Dist: numpy (<1.15,>=1.14)
Requires-Dist: pandas (<0.24,>=0.23)
Requires-Dist: pytest (<3.6,>=3.5)
